{
    "herf": "http://www.asx.com.au/asx/share-price-research/company/KLA",
    "GICSindustrygroup": "Materials",
    "Companyname": "KIRKLAND LAKE GOLD LTD",
    "ASXcode": "KLA",
    "data": {
        "summary": {
            "name_short": "KIRKLAND",
            "name_full": "KIRKLAND LAKE GOLD LTD",
            "code": "KLA",
            "primary_share_code": "KLA",
            "industry_group_name": "Materials",
            "delisting_date": null,
            "sector_name": "Metals & Mining",
            "name_abbrev": "KIRKLAND LAKE GOLD",
            "logo_image_url": "http://data.asx.com.au/data/1/image/logo/KLA?image_size=L&v=1511540646000",
            "foreign_exempt": true,
            "listing_date": "2017-11-30T00:00:00+1100",
            "registry_address": "YARRA FALLS, 452 JOHNSTON STREET, ABBOTSFORD, VIC, AUSTRALIA, 3067",
            "recent_announcement": false,
            "products": [
                "shares"
            ],
            "phone_number": "+1 416-840-7884",
            "mailing_address": "Level 2, 11-19 Bank Place, MELBOURNE, VIC, AUSTRALIA, 3000",
            "principal_activities": "Gold mining and exploration",
            "latest_annual_reports": [],
            "primary_share": {
                "volume": 0,
                "status": [],
                "year_high_price": 0,
                "indices": [],
                "deprecated_number_of_shares": 1000000,
                "previous_close_price": 0,
                "year_low_date": null,
                "last_trade_date": "2017-12-08T00:00:00+1100",
                "number_of_shares": 1000000,
                "eps": 0,
                "code": "KLA",
                "pe": 0,
                "offer_price": 0,
                "suspended": false,
                "last_price": 0,
                "deprecated_market_cap": 0,
                "day_low_price": 0,
                "open_price": 0,
                "year_high_date": null,
                "year_open_date": null,
                "market_cap": 0,
                "bid_price": 21.5,
                "desc_full": "Cdi 1:1 Foreign Exempt Xtse",
                "day_high_price": 0,
                "average_daily_volume": 0,
                "year_low_price": 0,
                "annual_dividend_yield": 0
            },
            "registry_phone_number": "1300 787 272",
            "web_address": "http://www.klgold.com",
            "registry_name": "COMPUTERSHARE INVESTOR SERVICES PTY LIMITED",
            "investor_relations_url": null
        },
        "details": {
            "directors": [],
            "secretaries": [
                {
                    "full_name": "Ms Jennifer Wagner",
                    "first_name": "Jennifer",
                    "roles": [
                        "Company Secretary"
                    ],
                    "salutation": "Ms",
                    "last_name": "Wagner",
                    "middle_name": ""
                }
            ]
        }
    }
}